{
    "@context": [
        "http://iiif.io/api/presentation/2/context.json",
        "http://codh.rois.ac.jp/iiif/curation/1/context.json"
    ],
    "@id": "https://nakamura196.github.io/nishikie/iiif/curation/isin1014/curation.json",
    "@type": "cr:Curation",
    "label": "Character List",
    "selections": [
        {
            "@id": "https://nakamura196.github.io/nishikie/iiif/curation/isin1014/range1",
            "@type": "sc:Range",
            "label": "Characters",
            "members": [
                {
                    "@id": "https://nakamura196.github.io/nishikie/iiif/isin1014/canvas/p1#xywh=60,99,818,1002",
                    "@type": "sc:Canvas",
                    "label": "vase",
                    "metadata": [
                        {
                            "label": "Method",
                            "value": "YOLO v3"
                        },
                        {
                            "label": "Score",
                            "value": "0.32903507"
                        },
                        {
                            "label": "Thumbnail Region",
                            "value": "60,99,818,1002"
                        },
                        {
                            "label": "Tag",
                            "value": "vase"
                        }
                    ]
                },
                {
                    "@id": "https://nakamura196.github.io/nishikie/iiif/isin1014/canvas/p1#xywh=613,1001,241,338",
                    "@type": "sc:Canvas",
                    "label": "person",
                    "metadata": [
                        {
                            "label": "Method",
                            "value": "YOLO v3"
                        },
                        {
                            "label": "Score",
                            "value": "0.8076254"
                        },
                        {
                            "label": "Thumbnail Region",
                            "value": "613,1001,241,338"
                        },
                        {
                            "label": "Tag",
                            "value": "person"
                        }
                    ]
                },
                {
                    "@id": "https://nakamura196.github.io/nishikie/iiif/isin1014/canvas/p2#xywh=708,758,154,509",
                    "@type": "sc:Canvas",
                    "label": "person",
                    "metadata": [
                        {
                            "label": "Method",
                            "value": "YOLO v3"
                        },
                        {
                            "label": "Score",
                            "value": "0.3694996"
                        },
                        {
                            "label": "Thumbnail Region",
                            "value": "708,758,154,509"
                        },
                        {
                            "label": "Tag",
                            "value": "person"
                        }
                    ]
                },
                {
                    "@id": "https://nakamura196.github.io/nishikie/iiif/isin1014/canvas/p2#xywh=528,847,169,454",
                    "@type": "sc:Canvas",
                    "label": "person",
                    "metadata": [
                        {
                            "label": "Method",
                            "value": "YOLO v3"
                        },
                        {
                            "label": "Score",
                            "value": "0.3842275"
                        },
                        {
                            "label": "Thumbnail Region",
                            "value": "528,847,169,454"
                        },
                        {
                            "label": "Tag",
                            "value": "person"
                        }
                    ]
                },
                {
                    "@id": "https://nakamura196.github.io/nishikie/iiif/isin1014/canvas/p2#xywh=636,756,176,189",
                    "@type": "sc:Canvas",
                    "label": "person",
                    "metadata": [
                        {
                            "label": "Method",
                            "value": "YOLO v3"
                        },
                        {
                            "label": "Score",
                            "value": "0.4294699"
                        },
                        {
                            "label": "Thumbnail Region",
                            "value": "636,756,176,189"
                        },
                        {
                            "label": "Tag",
                            "value": "person"
                        }
                    ]
                },
                {
                    "@id": "https://nakamura196.github.io/nishikie/iiif/isin1014/canvas/p2#xywh=620,825,194,497",
                    "@type": "sc:Canvas",
                    "label": "person",
                    "metadata": [
                        {
                            "label": "Method",
                            "value": "YOLO v3"
                        },
                        {
                            "label": "Score",
                            "value": "0.69172883"
                        },
                        {
                            "label": "Thumbnail Region",
                            "value": "620,825,194,497"
                        },
                        {
                            "label": "Tag",
                            "value": "person"
                        }
                    ]
                },
                {
                    "@id": "https://nakamura196.github.io/nishikie/iiif/isin1014/canvas/p2#xywh=155,910,172,416",
                    "@type": "sc:Canvas",
                    "label": "person",
                    "metadata": [
                        {
                            "label": "Method",
                            "value": "YOLO v3"
                        },
                        {
                            "label": "Score",
                            "value": "0.79062754"
                        },
                        {
                            "label": "Thumbnail Region",
                            "value": "155,910,172,416"
                        },
                        {
                            "label": "Tag",
                            "value": "person"
                        }
                    ]
                },
                {
                    "@id": "https://nakamura196.github.io/nishikie/iiif/isin1014/canvas/p2#xywh=269,877,176,466",
                    "@type": "sc:Canvas",
                    "label": "person",
                    "metadata": [
                        {
                            "label": "Method",
                            "value": "YOLO v3"
                        },
                        {
                            "label": "Score",
                            "value": "0.80227506"
                        },
                        {
                            "label": "Thumbnail Region",
                            "value": "269,877,176,466"
                        },
                        {
                            "label": "Tag",
                            "value": "person"
                        }
                    ]
                },
                {
                    "@id": "https://nakamura196.github.io/nishikie/iiif/isin1014/canvas/p2#xywh=39,659,221,300",
                    "@type": "sc:Canvas",
                    "label": "person",
                    "metadata": [
                        {
                            "label": "Method",
                            "value": "YOLO v3"
                        },
                        {
                            "label": "Score",
                            "value": "0.8660537"
                        },
                        {
                            "label": "Thumbnail Region",
                            "value": "39,659,221,300"
                        },
                        {
                            "label": "Tag",
                            "value": "person"
                        }
                    ]
                },
                {
                    "@id": "https://nakamura196.github.io/nishikie/iiif/isin1014/canvas/p2#xywh=11,872,177,442",
                    "@type": "sc:Canvas",
                    "label": "person",
                    "metadata": [
                        {
                            "label": "Method",
                            "value": "YOLO v3"
                        },
                        {
                            "label": "Score",
                            "value": "0.94692165"
                        },
                        {
                            "label": "Thumbnail Region",
                            "value": "11,872,177,442"
                        },
                        {
                            "label": "Tag",
                            "value": "person"
                        }
                    ]
                },
                {
                    "@id": "https://nakamura196.github.io/nishikie/iiif/isin1014/canvas/p2#xywh=404,882,205,459",
                    "@type": "sc:Canvas",
                    "label": "person",
                    "metadata": [
                        {
                            "label": "Method",
                            "value": "YOLO v3"
                        },
                        {
                            "label": "Score",
                            "value": "0.9503167"
                        },
                        {
                            "label": "Thumbnail Region",
                            "value": "404,882,205,459"
                        },
                        {
                            "label": "Tag",
                            "value": "person"
                        }
                    ]
                }
            ],
            "within": {
                "@id": "https://nakamura196.github.io/nishikie/iiif/isin1014/manifest.json",
                "@type": "sc:Manifest",
                "label": "おそろししのけだもの"
            }
        }
    ]
}