{
    "@context": [
        "http://iiif.io/api/presentation/2/context.json",
        "http://codh.rois.ac.jp/iiif/curation/1/context.json"
    ],
    "@id": "https://nakamura196.github.io/nishikie/iiif/curation/isin2010/curation.json",
    "@type": "cr:Curation",
    "label": "Character List",
    "selections": [
        {
            "@id": "https://nakamura196.github.io/nishikie/iiif/curation/isin2010/range1",
            "@type": "sc:Range",
            "label": "Characters",
            "members": [
                {
                    "@id": "https://nakamura196.github.io/nishikie/iiif/isin2010/canvas/p1#xywh=217,377,196,309",
                    "@type": "sc:Canvas",
                    "label": "person",
                    "metadata": [
                        {
                            "label": "Method",
                            "value": "YOLO v3"
                        },
                        {
                            "label": "Score",
                            "value": "0.3316525"
                        },
                        {
                            "label": "Thumbnail Region",
                            "value": "217,377,196,309"
                        },
                        {
                            "label": "Tag",
                            "value": "person"
                        }
                    ]
                },
                {
                    "@id": "https://nakamura196.github.io/nishikie/iiif/isin2010/canvas/p1#xywh=399,491,285,744",
                    "@type": "sc:Canvas",
                    "label": "person",
                    "metadata": [
                        {
                            "label": "Method",
                            "value": "YOLO v3"
                        },
                        {
                            "label": "Score",
                            "value": "0.7383268"
                        },
                        {
                            "label": "Thumbnail Region",
                            "value": "399,491,285,744"
                        },
                        {
                            "label": "Tag",
                            "value": "person"
                        }
                    ]
                },
                {
                    "@id": "https://nakamura196.github.io/nishikie/iiif/isin2010/canvas/p1#xywh=60,487,347,796",
                    "@type": "sc:Canvas",
                    "label": "person",
                    "metadata": [
                        {
                            "label": "Method",
                            "value": "YOLO v3"
                        },
                        {
                            "label": "Score",
                            "value": "0.77943724"
                        },
                        {
                            "label": "Thumbnail Region",
                            "value": "60,487,347,796"
                        },
                        {
                            "label": "Tag",
                            "value": "person"
                        }
                    ]
                },
                {
                    "@id": "https://nakamura196.github.io/nishikie/iiif/isin2010/canvas/p2#xywh=61,396,204,319",
                    "@type": "sc:Canvas",
                    "label": "person",
                    "metadata": [
                        {
                            "label": "Method",
                            "value": "YOLO v3"
                        },
                        {
                            "label": "Score",
                            "value": "0.65305233"
                        },
                        {
                            "label": "Thumbnail Region",
                            "value": "61,396,204,319"
                        },
                        {
                            "label": "Tag",
                            "value": "person"
                        }
                    ]
                },
                {
                    "@id": "https://nakamura196.github.io/nishikie/iiif/isin2010/canvas/p2#xywh=384,456,275,785",
                    "@type": "sc:Canvas",
                    "label": "person",
                    "metadata": [
                        {
                            "label": "Method",
                            "value": "YOLO v3"
                        },
                        {
                            "label": "Score",
                            "value": "0.8905977"
                        },
                        {
                            "label": "Thumbnail Region",
                            "value": "384,456,275,785"
                        },
                        {
                            "label": "Tag",
                            "value": "person"
                        }
                    ]
                },
                {
                    "@id": "https://nakamura196.github.io/nishikie/iiif/isin2010/canvas/p2#xywh=589,456,273,767",
                    "@type": "sc:Canvas",
                    "label": "person",
                    "metadata": [
                        {
                            "label": "Method",
                            "value": "YOLO v3"
                        },
                        {
                            "label": "Score",
                            "value": "0.94511133"
                        },
                        {
                            "label": "Thumbnail Region",
                            "value": "589,456,273,767"
                        },
                        {
                            "label": "Tag",
                            "value": "person"
                        }
                    ]
                }
            ],
            "within": {
                "@id": "https://nakamura196.github.io/nishikie/iiif/isin2010/manifest.json",
                "@type": "sc:Manifest",
                "label": "世の中のうらない"
            }
        }
    ]
}